{"name": "https://github.com/ShifanaJishadh Shifana", "email": "shifanajishadh@gmail.com", "mobile_number": "8907150600", "skills": ["Numpy", "System", "English", "Safety", "Pandas", "Technical", "Linux", "Python", "Analysis", "Machine learning", "Android", "Engineering", "Email", "Word", "Html", "Security", "Wordpress", "Technical skills", "Algorithms", "Github", "Data analysis", "Statistics", "C", "Jupyter", "Programming", "Keras", "Tensorflow", "Windows", "Hadoop", "Mobile"], "college_name": null, "degree": null, "designation": null, "experience": null, "company_names": null, "no_of_pages": 2, "total_experience": 0}